fingerflow/__init__.py
fingerflow/extractor/__init__.py
fingerflow/extractor/classify_net.py
fingerflow/extractor/constants.py
fingerflow/extractor/core_net.py
fingerflow/extractor/extractor.py
fingerflow/extractor/minutiae_net.py
fingerflow/extractor/utils.py
fingerflow/extractor/ClassifyNet/__init__.py
fingerflow/extractor/ClassifyNet/classify_net_model.py
fingerflow/extractor/ClassifyNet/utils.py
fingerflow/extractor/CoreNet/__init__.py
fingerflow/extractor/CoreNet/constants.py
fingerflow/extractor/CoreNet/core_net_model.py
fingerflow/extractor/CoreNet/custom_layers.py
fingerflow/extractor/CoreNet/utils.py
fingerflow/extractor/MinutiaeNet/__init__.py
fingerflow/extractor/MinutiaeNet/CoarseNet/__init__.py
fingerflow/extractor/MinutiaeNet/CoarseNet/coarse_net_model.py
fingerflow/extractor/MinutiaeNet/CoarseNet/coarse_net_run.py
fingerflow/extractor/MinutiaeNet/CoarseNet/coarse_net_train.py
fingerflow/extractor/MinutiaeNet/CoarseNet/coarse_net_utils.py
fingerflow/extractor/MinutiaeNet/CoarseNet/loss_functions.py
fingerflow/extractor/MinutiaeNet/CoarseNet/minutiae_net_utils.py
fingerflow/extractor/MinutiaeNet/FineNet/__init__.py
fingerflow/extractor/MinutiaeNet/FineNet/fine_net_model.py
fingerflow/extractor/MinutiaeNet/FineNet/fine_net_train.py
fingerflow/matcher/__init__.py
fingerflow/matcher/matcher.py
fingerflow/matcher/verify_net.py
fingerflow/matcher/VerifyNet/__init__.py
fingerflow/matcher/VerifyNet/constants.py
fingerflow/matcher/VerifyNet/utils.py
fingerflow/matcher/VerifyNet/verify_net_model.py
fingerflow/matcher/VerifyNet/verify_net_train.py
fingerflow/matcher/VerifyNet/verify_net_train_experimental.py
fingerflow-3.0.1.dist-info/LICENSE
fingerflow-3.0.1.dist-info/METADATA
fingerflow-3.0.1.dist-info/WHEEL
fingerflow-3.0.1.dist-info/top_level.txt
fingerflow-3.0.1.dist-info/RECORD
