Metadata-Version: 2.1
Name: fingerflow
Version: 3.0.1
Summary: FingerFlow
Home-page: https://github.com/jakubarendac/fingerflow
Author: Jakub Arendac
Author-email: jakub.arendac105@gmail.com
Project-URL: Bug Tracker, https://github.com/jakubarendac/fingerflow/issues
Classifier: Programming Language :: Python :: 3
Classifier: License :: OSI Approved :: MIT License
Classifier: Operating System :: OS Independent
Requires-Python: >=3.7
License-File: LICENSE
Requires-Dist: Keras-Applications (>=1.0.8)
Requires-Dist: matplotlib (>=3.4.2)
Requires-Dist: numpy (>=1.19.5)
Requires-Dist: opencv-python (>=4.5.3.36)
Requires-Dist: pandas (>=1.3.1)
Requires-Dist: scikit-image (>=0.18.3)
Requires-Dist: scipy (>=1.6.2)
Requires-Dist: tensorflow (>=2.5.1)
